Workbook

Sheet 明细
A1: 费用明细表 · 服装独立站出海一期（2个月执行周期）
A2: 蓝色单元格 = 可手动调整的输入项 · 方案A 保守 / 方案B 标准推荐 · 人工薪资不计入
A4: 分类 | B4: 项目名称 | C4: 说明 | D4: 必要性 | E4: 单价A (¥) | F4: 单价B (¥) | G4: 数量 | H4: 方案A 合计 | I4: 方案B 合计 | J4: 备注 / 数据来源 | K4: 备注 / 数据来源
A5: 建站基础 | B5: 域名 (.com) | C5: 品牌专属.com域名，首年注册费 | D5: 必须 | E5: 一次性 | F5: 85 | G5: 85 | H5: 1 | I5: =F5*H5 | J5: =G5*H5 | K5: Namecheap/阿里云约¥70-100/年
A6: 建站基础 | B6: 云服务器 | C6: 方案A: Vercel/Netlify 静态托管（免费） 方案B: 腾讯云轻量 2核2G ¥99/月 | D6: 必须 | E6: 月费×2 | F6: 0 | G6: 99 | H6: 2 | I6: =F6*H6 | J6: =G6*H6 | K6: 纯展示站+表单场景Vercel免费版完全足够
A7: 建站基础 | B7: SSL证书 | C7: Let's Encrypt 免费HTTPS，随平台自动配置 | D7: 必须 | E7: 免费 | F7: 0 | G7: 0 | H7: 1 | I7: =F7*H7 | J7: =G7*H7 | K7: Vercel/腾讯云均自动签发，零成本
A8: AI开发工具 | B8: AI编程助手 (Cursor) | C8: Vibecoding核心工具 方案A: 免费额度 方案B: Pro $20/月 | D8: 建议 | E8: 月费×2 | F8: 0 | G8: 145 | H8: 2 | I8: =F8*H8 | J8: =G8*H8 | K8: ¥145≈$20×7.25；Pro版含完整AI补全配额，免费版有月限额
A9: 设计工具 | B9: Canva 设计订阅 | C9: 社媒内容/营销图文/产品主图制作 方案A: 免费版 方案B: Canva Pro ¥99/月 | D9: 建议 | E9: 月费×2 | F9: 0 | G9: 99 | H9: 2 | I9: =F9*H9 | J9: =G9*H9 | K9: Pro版含背景移除/品牌套件；免费版Phase 1勉强可用
A10: 网络工具 | B10: VPN 工具（2人） | C10: 国内访问 TikTok / LinkedIn / Instagram 必需 ¥30/人/月 × 2人 | D10: 必须 | E10: 月费×2 | F10: 60 | G10: 60 | H10: 2 | I10: =F10*H10 | J10: =G10*H10 | K10: 两方案相同，这是硬性必需项不可省
A11: 社媒账号 | B11: TikTok 境外手机号 | C11: 注册 TikTok 国际版需境外号码 虚拟号服务(smsactivate.org等) | D11: 必须 | E11: 一次性 | F11: 30 | G11: 30 | H11: 1 | I11: =F11*H11 | J11: =G11*H11 | K11: 约¥20-50/个；建议多备1个号以防封号
A12: 社媒账号 | B12: LinkedIn Premium | C12: B2B主动开发：InMail + 高级买家搜索 方案A: 免费版 方案B: Premium $40/月 | D12: 可选 | E12: 月费×2 | F12: 0 | G12: 290 | H12: 2 | I12: =F12*H12 | J12: =G12*H12 | K12: ¥290≈$40×7.25；可只订1个月测试，显著提升B端触达效率
A13: 社媒账号 | B13: 认证蓝V (TikTok/INS) | C13: Phase 1 不建议，专注内容质量更重要 账号积累粉丝基数后再考虑 | D13: 不建议 | E13: 免费 | F13: 0 | G13: 0 | H13: 1 | I13: =F13*H13 | J13: =G13*H13 | K13: 两方案均不纳入，避免资源分散
A14: 商务通讯 | B14: 商务邮箱 | C14: 品牌域名邮箱 brand@yourdomain.com Zoho Mail 1用户免费版 | D14: 建议 | E14: 免费 | F14: 0 | G14: 0 | H14: 1 | I14: =F14*H14 | J14: =G14*H14 | K14: 大幅提升B端可信度；Zoho免费版功能已满足需求
A15: 商务通讯 | B15: WhatsApp Business | C15: 全球B端客户首选即时通讯，免费 可与TikTok共用同一境外号 | D15: 必须 | E15: 免费 | F15: 0 | G15: 0 | H15: 1 | I15: =F15*H15 | J15: =G15*H15 | K15: APP免费；务必开通，大部分海外买家首选WhatsApp沟通
A16: 产品验证 | B16: POD 样品打样 | C16: 首批 3-5 件样品，推广前必须验证实物品质 避免客户投诉影响口碑 | D16: 建议 | E16: 一次性 | F16: 300 | G16: 300 | H16: 1 | I16: =F16*H16 | J16: =G16*H16 | K16: 成本视款式复杂度而定；此处¥300为保守中间估算
... A20: 效率工具 | B20: Google Analytics | C20: 独立站流量与用户行为分析，必装，完全免费 | D20: 必须 | E20: 免费 | F20: 0 | G20: 0 | H20: 1 | I20: =F20*H20 | J20: =G20*H20 | K20: 与独立站代码集成，零成本，Phase 1必须配置
A21: 合计（2个月全部预算） | I21: =SUM(I5:I20) | J21: =SUM(J5:J20)
A23: ⚡ 方案A = Vercel免费服务器 + Cursor免费版 + Canva免费版 + 无LinkedIn Premium + 不投流 · 方案B = 腾讯云¥99/月 + Cursor Pro + Canva Pro + LinkedIn Premium + ¥500测试投流 · 人工薪资、样品生产成本（非打样）、后端交付均不计入

Sheet 成本总览
A1: 服装独立站出海 · 一期成本总览（2个月）
A2: 两人团队 · 服装POD独立站 · 目标：1-2个月内首单成交 · 人工成本不计入
A4: 方案 A · 保守最低成本 | C4: 方案 B · 标准推荐配置
A5: =明细!I21 | C5: =明细!J21
A6: Vercel免费版 · Cursor免费 · Canva免费 · 无LinkedIn · 全自然流量 | C6: 腾讯云 · Cursor Pro · Canva Pro · LinkedIn Premium · ¥500测试投流
A8: 分类 | B8: 方案A小计 | C8: 方案B小计 | D8: 主要差异说明
A9: 建站基础 | B9: =SUMIF(明细!$A$5:$A$20,A9,明细!$I$5:$I$20) | C9: =SUMIF(明细!$A$5:$A$20,A9,明细!$J$5:$J$20) | D9: 方案A用Vercel免费，方案B腾讯云¥99/月
A10: AI开发工具 | B10: =SUMIF(明细!$A$5:$A$20,A10,明细!$I$5:$I$20) | C10: =SUMIF(明细!$A$5:$A$20,A10,明细!$J$5:$J$20) | D10: 方案A用Cursor免费额度，方案B Pro $20/月×2
A11: 设计工具 | B11: =SUMIF(明细!$A$5:$A$20,A11,明细!$I$5:$I$20) | C11: =SUMIF(明细!$A$5:$A$20,A11,明细!$J$5:$J$20) | D11: 方案A Canva免费版，方案B Pro ¥99/月×2
A12: 网络工具 | B12: =SUMIF(明细!$A$5:$A$20,A12,明细!$I$5:$I$20) | C12: =SUMIF(明细!$A$5:$A$20,A12,明细!$J$5:$J$20) | D12: 两方案相同（硬性必需，不可省）
A13: 社媒账号 | B13: =SUMIF(明细!$A$5:$A$20,A13,明细!$I$5:$I$20) | C13: =SUMIF(明细!$A$5:$A$20,A13,明细!$J$5:$J$20) | D13: 方案B含LinkedIn Premium ¥290/月×2
A14: 商务通讯 | B14: =SUMIF(明细!$A$5:$A$20,A14,明细!$I$5:$I$20) | C14: =SUMIF(明细!$A$5:$A$20,A14,明细!$J$5:$J$20) | D14: 两方案均免费（Zoho+WhatsApp）
A15: 产品验证 | B15: =SUMIF(明细!$A$5:$A$20,A15,明细!$I$5:$I$20) | C15: =SUMIF(明细!$A$5:$A$20,A15,明细!$J$5:$J$20) | D15: 两方案相同（打样¥300+快递¥250）
A16: 流量推广 | B16: =SUMIF(明细!$A$5:$A$20,A16,明细!$I$5:$I$20) | C16: =SUMIF(明细!$A$5:$A$20,A16,明细!$J$5:$J$20) | D16: 方案A全靠自然流量，方案B第2月¥500测试
A17: 效率工具 | B17: =SUMIF(明细!$A$5:$A$20,A17,明细!$I$5:$I$20) | C17: =SUMIF(明细!$A$5:$A$20,A17,明细!$J$5:$J$20) | D17: 两方案均免费（HubSpot+Google Analytics）
A18: 两个月总预算 | B18: =明细!I21 | C18: =明细!J21
A20: 📌 未包含的成本
A21: 人工薪资（2人团队工资/劳务）
A22: 正式订单生产成本（客户付款后按需生产）
A23: 后端交付及客户成交（外部团队承接，不计入）
A24: 网站上线后的持续运营/维护人时
A26: 💡 成本控制建议
A27: 第1个月优先走方案A，验证路径后第2个月按需升级方案B工具
A28: LinkedIn Premium 可先免费版+手动搜索，如效率太低再开Pro
A29: 投流预算建议等有5-10条高质量内容后再开启，避免浪费
A30: Cursor免费版+免费Claude/GPT配合使用，可显著延迟付费升级时间

Sheet 审核建议
A1: 一期启动成本 · 必要性审核与补充说明
A2: 审核您提到的每一项，并补充您可能遗漏的关键成本
A4: 您提到的项目 → 审核结论
A5: 您提到的项目 | B5: 结论 | C5: 说明 | D5: 预算影响
A6: Vibecoding 建站方式 | B6: ✅ 完全可行 | C6: 对展示站+表单场景非常合适。推荐 Cursor + Next.js/React + Vercel 部署。无需传统雇佣开发，大幅降低技术门槛与费用。 | D6: 需AI编程工具（可免费）
A7: 腾讯云服务器 | B7: ⚠️ 可替代 | C7: 对纯前端展示站，Vercel/Netlify 免费版已完全满足需求（自动HTTPS/CDN/全球节点）。腾讯云更适合有复杂后端需求的场景。Phase 1 推荐先用免费方案。 | D7: 方案A省¥198
A8: 购买域名 | B8: ✅ 必须 | C8: 无条件必须。建议购买 .com 域名，约¥70-100/年。推荐 Namecheap（国际结算）或阿里云（国内付款方便）。 | D8: 约¥85，两方案相同
A9: TK等社媒账号从0建设 | B9: ✅ 必须，但账号注册本身免费 | C9: TikTok国际版、Instagram、LinkedIn 账号注册均免费。真实成本是注册TikTok国际版需要境外手机号（¥20-50）。 | D9: 境外号¥30，其余免费
A10: 社媒认证费用 | B10: ⚠️ Phase 1 不建议 | C10: TikTok / Instagram 普通创作者认证免费；付费认证（如INS蓝V $14.99/月）对Phase 1 ROI极低，不建议纳入预算。真正的成本是境外手机号注册费。 | D10: 已从预算中排除
A11: 两人团队 | B11: ✅ 合理 | C11: 2人分工：1人负责内容运营+社媒，1人负责建站+设计+B2B开发。人工薪资不计入工具成本预算，按团队实际情况决定。 | D11: 不计入工具预算
A12: 外部团队负责成交，不计入 | B12: ✅ 合理 | C12: 独立站定位为展示+询盘入口，外部团队处理后续谈单成交。简化了独立站功能需求（无需复杂购物车/支付），建站成本可控。 | D12: 已从预算中排除
A15: 补充项目 → 您可能遗漏的关键成本
A16: 补充项目 | B16: 优先级 | C16: 原因说明 | D16: 预算影响
A17: VPN 工具（2人） | B17: 🔴 必须 | C17: 从国内运营海外TikTok/LinkedIn/Instagram是硬性需求，您提到社媒运营但未提VPN成本。¥30/人/月，2人合计¥60/月。 | D17: ¥120（2个月）
A18: AI 编程助手（Cursor等） | B18: 🟡 建议 | C18: 您说要用Vibecoding方式建站，但未提AI工具成本。Cursor免费版有月度配额限制；Pro版$20/月可确保建站期间不断流。 | D18: 方案B +¥290
A19: 设计工具（Canva Pro） | B19: 🟡 建议 | C19: 社媒内容生产、产品主图制作需要设计工具。Canva免费版功能受限，Pro版¥99/月含背景去除、品牌套件等核心功能。 | D19: 方案B +¥198
A20: POD 样品打样 | B20: 🟡 建议 | C20: 推广前必须验证实物品质。POD产品与展示图之间存在差异，如果没有打过样直接推广，可能产生客诉影响口碑。建议首批打3-5件。 | D20: ¥300（一次性）
A21: 国际快递（寄样品） | B21: 🟡 建议 | C21: B2B询盘中，买家几乎100%要求看样品。能主动寄样是促成首单的关键信任动作，约¥200-350/次。 | D21: ¥250（约1次）
A22: 商务邮箱（Zoho免费） | B22: 🟢 免费 | C22: brand@yourdomain.com 对B端客户信任度至关重要。Zoho Mail 1用户免费版完全满足，零额外成本。 | D22: ¥0（免费）
A23: LinkedIn Premium（可选） | B23: 🔵 可选 | C23: B2B主动开发时，Premium的InMail功能显著提升触达率。如果预算有限可先用免费版，成交后再考虑升级。 | D23: 方案B +¥580
